secp256k1-0.14.0.dist-info/RECORD
secp256k1-0.14.0.dist-info/WHEEL
secp256k1-0.14.0.dist-info/top_level.txt
secp256k1-0.14.0.dist-info/METADATA
secp256k1-0.14.0.dist-info/licenses/LICENSE
secp256k1/__init__.py
secp256k1/__main__.py
secp256k1/_libsecp256k1.cpython-310-darwin.so
