Metadata-Version: 2.1
Name: secp256k1
Version: 0.14.0
Summary: FFI bindings to libsecp256k1
Home-page: https://github.com/rustyrussell/secp256k1-py
Author: Ludvig Broberg
Author-email: lud@tutanota.com
Maintainer: Rusty Russell
Maintainer-email: rusty@rustcorp.com.au
License: MIT
Platform: UNKNOWN
Classifier: Intended Audience :: Developers
Classifier: License :: OSI Approved :: MIT License
Classifier: Programming Language :: Python :: 2
Classifier: Programming Language :: Python :: 3
Classifier: Programming Language :: Python :: Implementation :: CPython
Classifier: Programming Language :: Python :: Implementation :: PyPy
Classifier: Topic :: Software Development :: Libraries
Classifier: Topic :: Security :: Cryptography
